PicAssert/Assert.py
PicAssert/__init__.py
PicAssert-1.3.1.dist-info/LICENSE.txt
PicAssert-1.3.1.dist-info/METADATA
PicAssert-1.3.1.dist-info/WHEEL
PicAssert-1.3.1.dist-info/top_level.txt
PicAssert-1.3.1.dist-info/RECORD
